{
  "system": "5e2024",
  "resource_id": "item",
  "stats": {
    "name": {
      "value": "Elephant"
    },
    "source": {
      "value": "phb"
    },
    "description": {
      "value": "Speed: 40, Carrying Capacity: 1320 lb"
    },
    "type": {
      "value": "mount"
    },
    "cost": {
      "value": {
        "system": "5e2024",
        "resource_id": "cost",
        "stats": {
          "value": {
            "value": 20.0
          },
          "unit": {
            "value": "platinum"
          },
          "updated_at": {
            "value": "2024-12-20T18:50:35.683776"
          },
          "id": "bb6cca22-37d6-4d02-816d-6bd22f10cd49"
        }
      }
    },
    "weight": {
      "value": {
        "system": "5e2024",
        "resource_id": "weight",
        "stats": {
          "unit": {
            "value": "pounds"
          },
          "updated_at": {
            "value": "2024-12-20T18:50:35.683781"
          },
          "id": "16d67300-aa8e-4345-83e3-e9803bdb0685"
        }
      }
    },
    "rarity": {
      "value": "none"
    },
    "is_magic": {
      "value": false
    },
    "requires_attunement": {
      "value": false
    },
    "is_cursed": {
      "value": false
    },
    "is_intelligent": {
      "value": false
    },
    "is_spellcasting_focus": {
      "value": false
    },
    "effects": {
      "value": []
    },
    "updated_at": {
      "value": "2024-12-20T18:50:35.683783"
    },
    "id": "elephant"
  }
}
