{
  "system": "5e2024",
  "resource_id": "item",
  "stats": {
    "name": {
      "value": "Bullseye Lantern"
    },
    "source": {
      "value": "phb"
    },
    "description": {
      "value": "A Bullseye Lantern burns Oil as fuel to cast Bright Light in a 60-foot Cone and Dim Light for an additional 60 feet"
    },
    "type": {
      "value": "adventuring_gear"
    },
    "cost": {
      "value": {
        "system": "5e2024",
        "resource_id": "cost",
        "stats": {
          "value": {
            "value": 1.0
          },
          "unit": {
            "value": "platinum"
          },
          "updated_at": {
            "value": "2024-12-20T18:50:35.667854"
          },
          "id": "7b649062-3136-4483-8289-fc282080c23c"
        }
      }
    },
    "weight": {
      "value": {
        "system": "5e2024",
        "resource_id": "weight",
        "stats": {
          "value": {
            "value": 2
          },
          "unit": {
            "value": "pounds"
          },
          "updated_at": {
            "value": "2024-12-20T18:50:35.667859"
          },
          "id": "41955c67-7fe8-43da-a0fc-bced5a71f41c"
        }
      }
    },
    "rarity": {
      "value": "none"
    },
    "is_magic": {
      "value": false
    },
    "requires_attunement": {
      "value": false
    },
    "is_cursed": {
      "value": false
    },
    "is_intelligent": {
      "value": false
    },
    "is_spellcasting_focus": {
      "value": false
    },
    "effects": {
      "value": []
    },
    "updated_at": {
      "value": "2024-12-20T18:50:35.667862"
    },
    "id": "bullseye_lantern"
  }
}
