{
  "system": "5e2024",
  "resource_id": "item",
  "stats": {
    "name": {
      "value": "Oil of Taggit"
    },
    "source": {
      "value": "dmg"
    },
    "description": {
      "value": "A creature subjected to Oil of Taggit must succeed on a DC 13 Constitution saving throw or have the Poisoned condition for 24 hours. The creature also has the Unconscious condition while Poisoned in this way. It wakes up if it takes damage"
    },
    "type": {
      "value": "poison"
    },
    "cost": {
      "value": {
        "system": "5e2024",
        "resource_id": "cost",
        "stats": {
          "value": {
            "value": 40.0
          },
          "unit": {
            "value": "platinum"
          },
          "updated_at": {
            "value": "2024-12-20T18:50:35.722105"
          },
          "id": "a407f9b8-34be-4d87-895e-c74ffc01b3f1"
        }
      }
    },
    "weight": {
      "value": {
        "system": "5e2024",
        "resource_id": "weight",
        "stats": {
          "unit": {
            "value": "pounds"
          },
          "updated_at": {
            "value": "2024-12-20T18:50:35.722110"
          },
          "id": "fe912aab-1851-4345-85af-b18ee496225d"
        }
      }
    },
    "rarity": {
      "value": "none"
    },
    "is_magic": {
      "value": false
    },
    "requires_attunement": {
      "value": false
    },
    "is_cursed": {
      "value": false
    },
    "is_intelligent": {
      "value": false
    },
    "is_spellcasting_focus": {
      "value": false
    },
    "effects": {
      "value": []
    },
    "updated_at": {
      "value": "2024-12-20T18:50:35.722113"
    },
    "id": "oil_of_taggit"
  }
}
