{
  "system": "5e2024",
  "resource_id": "item",
  "stats": {
    "name": {
      "value": "Pepper"
    },
    "source": {
      "value": "dmg"
    },
    "description": {
      "value": ""
    },
    "type": {
      "value": "trade_good"
    },
    "cost": {
      "value": {
        "system": "5e2024",
        "resource_id": "cost",
        "stats": {
          "value": {
            "value": 2.0
          },
          "unit": {
            "value": "gold"
          },
          "updated_at": {
            "value": "2024-12-20T18:50:35.825270"
          },
          "id": "0b40baf9-2a19-4ca3-b49a-6729644da750"
        }
      }
    },
    "weight": {
      "value": {
        "system": "5e2024",
        "resource_id": "weight",
        "stats": {
          "value": {
            "value": 1
          },
          "unit": {
            "value": "pounds"
          },
          "updated_at": {
            "value": "2024-12-20T18:50:35.825276"
          },
          "id": "94fcc408-9291-4690-b7b5-3a5398525af1"
        }
      }
    },
    "rarity": {
      "value": "none"
    },
    "is_magic": {
      "value": false
    },
    "requires_attunement": {
      "value": false
    },
    "is_cursed": {
      "value": false
    },
    "is_intelligent": {
      "value": false
    },
    "is_spellcasting_focus": {
      "value": false
    },
    "effects": {
      "value": []
    },
    "updated_at": {
      "value": "2024-12-20T18:50:35.825278"
    },
    "id": "pepper"
  }
}
