{
  "system": "5e2024",
  "resource_id": "item",
  "stats": {
    "name": {
      "value": "Ioun Stone, Greater Absorption"
    },
    "source": {
      "value": "dmg"
    },
    "description": {
      "value": "Roughly marble sized, Ioun Stones are named after Ioun, a god of knowledge and prophecy revered on some worlds. Many types of Ioun Stones exist, each type a distinct combination of shape and color.\n\nWhen you take a Magic action to toss an Ioun Stone into the air, the stone orbits your head at a distance of 1d3 feet, conferring its benefit to you while doing so. You can have up to three Ioun Stones orbiting your head at the same time.\n\nEach Ioun Stone orbiting your head is considered to be an object you are wearing. The orbiting stone avoids contact with other creatures and objects, adjusting its orbit to avoid collisions and thwarting all attempts by other creatures to attack or snatch it.\n\nAs a Utilize action, you can seize and stow any number of Ioun Stones orbiting your head. If your Attunement to an Ioun Stone ends while it's orbiting your head, the stone falls as though you had dropped it.\n\nWhile this marbled lavender and green ellipsoid orbits your head, you can take a Reaction to cancel a spell of level 8 or lower cast by a creature you can see. A canceled spell has no effect, and any resources used to cast it are wasted. Once the stone has canceled 20 levels of spells, it burns out, turns dull gray, and loses its magic"
    },
    "type": {
      "value": "wondrous"
    },
    "cost": {
      "value": {
        "system": "5e2024",
        "resource_id": "cost",
        "stats": {
          "value": {
            "value": 0
          },
          "unit": {
            "value": "gold"
          },
          "updated_at": {
            "value": "2024-12-20T18:50:35.777658"
          },
          "id": "801f7691-37cf-4a7a-a431-a28c5817419d"
        }
      }
    },
    "weight": {
      "value": {
        "system": "5e2024",
        "resource_id": "weight",
        "stats": {
          "value": {
            "value": 0
          },
          "unit": {
            "value": "pounds"
          },
          "updated_at": {
            "value": "2024-12-20T18:50:35.777662"
          },
          "id": "c535e849-ec8a-4f28-86b0-8c0c98dbf7c4"
        }
      }
    },
    "rarity": {
      "value": "legendary"
    },
    "is_magic": {
      "value": true
    },
    "requires_attunement": {
      "value": true
    },
    "is_cursed": {
      "value": false
    },
    "is_intelligent": {
      "value": false
    },
    "is_spellcasting_focus": {
      "value": false
    },
    "effects": {
      "value": [
        {
          "system": "5e2024",
          "resource_id": "effect",
          "stats": {
            "name": {
              "value": "Remaining Cancelation Levels"
            },
            "trigger_type": {
              "value": "active"
            },
            "trigger_condition": {
              "value": {
                "system": "5e2024",
                "resource_id": "trigger_condition_or",
                "stats": {
                  "id": "3d71a8c9-d0a7-4ee1-8695-d4e203c7cd7f"
                }
              }
            },
            "has_charges": {
              "value": true
            },
            "charge_type": {
              "value": "constant"
            },
            "recharge_type": {
              "value": "formula"
            },
            "recharge_event": {
              "value": "manual"
            },
            "max_charges_constant": {
              "value": 20
            },
            "recharges": {
              "value": {
                "system": "5e2024",
                "resource_id": "dice_roll",
                "stats": {
                  "dice_amount": {
                    "value": 0
                  },
                  "dice_type": {
                    "value": "d4"
                  },
                  "constant": {
                    "value": 0
                  },
                  "updated_at": {
                    "value": "2024-12-20T18:50:35.777671"
                  },
                  "id": "6f5fc6e1-0448-453b-8cdf-5e2a2ae1209d"
                }
              }
            },
            "type": {
              "value": "none"
            },
            "events": {
              "value": ""
            },
            "stat": {
              "value": "$character.strength_score"
            },
            "advantage_stat": {
              "value": "$character.strength_score"
            },
            "updated_at": {
              "value": "2024-12-20T18:50:35.777677"
            },
            "id": "a860891e-1928-4c6a-a503-7f5b7c3bf504"
          }
        }
      ]
    },
    "updated_at": {
      "value": "2024-12-20T18:50:35.777679"
    },
    "id": "ioun_stone,_greater_absorption"
  }
}
